journey_orchestrate/__init__.py
journey_orchestrate/main.py
journey_orchestrate-0.0.8.dist-info/METADATA
journey_orchestrate-0.0.8.dist-info/WHEEL
journey_orchestrate-0.0.8.dist-info/top_level.txt
journey_orchestrate-0.0.8.dist-info/RECORD
