Metadata-Version: 2.1
Name: journey_orchestrate
Version: 0.0.8
Summary: Customer Journey Orchestration Utility
Author: Dhivya Nagasubramanian
Author-email: nagas021@alumni.umn.edu
Classifier: Programming Language :: Python :: 3
Classifier: License :: OSI Approved :: MIT License
Classifier: Operating System :: OS Independent
Requires-Python: >=3.6
